holotools/__init__.py
holotools/alignment.py
holotools/barrnap.py
holotools/biom.py
holotools/biop.py
holotools/blast.py
holotools/clustering.py
holotools/eln.py
holotools/eutils.py
holotools/ostools.py
holotools/patentin.py
holotools/progress.py
holotools/qiime.py
holotools/seqclass.py
holotools/sort.py
holotools/std.py
holotools/tests.py
holotools/trim.py
holotools/truncate.py
holotools/web.py
holotools-0.0.25.dist-info/LICENSE
holotools-0.0.25.dist-info/METADATA
holotools-0.0.25.dist-info/WHEEL
holotools-0.0.25.dist-info/top_level.txt
holotools-0.0.25.dist-info/RECORD
