Metadata-Version: 2.1
Name: holotools
Version: 0.0.25
Summary: Python Code Base Used by the Holobiome Team
Home-page: https://github.com/HolobiomeProject/holotools
Author: Barry Guglielmo
Author-email: barryguglielmo@gmail.com
License: UNKNOWN
Platform: UNKNOWN
Requires-Dist: pandas
Provides-Extra: dev
Requires-Dist: pytest (>=3.6) ; extra == 'dev'
